ai/backend/cli/VERSION
ai/backend/cli/__init__.py
ai/backend/cli/__main__.py
ai/backend/cli/extensions.py
ai/backend/cli/interaction.py
ai/backend/cli/loader.py
ai/backend/cli/main.py
ai/backend/cli/params.py
ai/backend/cli/py.typed
ai/backend/cli/types.py
backend_ai_cli-26.1.0.dist-info/METADATA
backend_ai_cli-26.1.0.dist-info/WHEEL
backend_ai_cli-26.1.0.dist-info/entry_points.txt
backend_ai_cli-26.1.0.dist-info/namespace_packages.txt
backend_ai_cli-26.1.0.dist-info/top_level.txt
backend_ai_cli-26.1.0.dist-info/RECORD
